cmlabs/__init__.py
cmlabs/differentiate/__init__.py
cmlabs/differentiate/_differentiate.py
cmlabs/differentiate/tests/__init__.py
cmlabs/differentiate/tests/test_differentiate.py
cmlabs/integrate/__init__.py
cmlabs/integrate/_integrate.py
cmlabs/integrate/tests/__init__.py
cmlabs/integrate/tests/test_integrate.py
cmlabs/interpolate/__init__.py
cmlabs/interpolate/_cubic.py
cmlabs/interpolate/_interpolate.py
cmlabs/interpolate/tests/__init__.py
cmlabs/interpolate/tests/test_interpolate.py
cmlabs/linalg/__init__.py
cmlabs/linalg/_linalg.py
cmlabs/linalg/tests/__init__.py
cmlabs/linalg/tests/test_linalg.py
cmlabs/optimize/__init__.py
cmlabs/optimize/_optimize.py
cmlabs/optimize/tests/__init__.py
cmlabs/optimize/tests/test_optimize.py
cmlabs-0.2.2.dist-info/licenses/LICENSE
cmlabs-0.2.2.dist-info/METADATA
cmlabs-0.2.2.dist-info/WHEEL
cmlabs-0.2.2.dist-info/top_level.txt
cmlabs-0.2.2.dist-info/RECORD
